public class com.example.Test1 {
  public com.example.Test1();
    Code:
       0: aload_0
       1: invokespecial #1                  // Method java/lang/Object."<init>":()V
       4: return

  public void method1();
    Code:
       0: getstatic     #2                  // Field java/lang/System.out:Ljava/io/PrintStream;
       3: ldc           #3                  // String HELLO WORLD
       5: invokevirtual #4                  // Method java/io/PrintStream.println:(Ljava/lang/String;)V
       8: return

  public void method2();
    Code:
       0: ldc           #3                  // String HELLO WORLD
       2: astore_1
       3: getstatic     #2                  // Field java/lang/System.out:Ljava/io/PrintStream;
       6: aload_1
       7: invokevirtual #4                  // Method java/io/PrintStream.println:(Ljava/lang/String;)V
      10: return

  public void method3();
    Code:
       0: getstatic     #2                  // Field java/lang/System.out:Ljava/io/PrintStream;
       3: ldc           #5                  // String HELLO
       5: invokevirtual #6                  // Method java/io/PrintStream.append:(Ljava/lang/CharSequence;)Ljava/io/PrintStream;
       8: pop
       9: getstatic     #2                  // Field java/lang/System.out:Ljava/io/PrintStream;
      12: invokevirtual #7                  // Method java/io/PrintStream.println:()V
      15: return
}